simple_calculator_tsai/__init__.py
simple_calculator_tsai-0.1.0.dist-info/METADATA
simple_calculator_tsai-0.1.0.dist-info/WHEEL
simple_calculator_tsai-0.1.0.dist-info/top_level.txt
simple_calculator_tsai-0.1.0.dist-info/RECORD
