Metadata-Version: 2.4
Name: simple-calculator-tsai
Version: 0.1.0
Summary: A simple calculator package with basic arithmetic operations.
Home-page: https://pypi.org/project/simple-calculator-tsai/
Author: Your Name
Author-email: your.email@example.com
License: MIT
Classifier: Programming Language :: Python :: 3
Classifier: License :: OSI Approved :: MIT License
Classifier: Operating System :: OS Independent
Requires-Python: >=3.6
Dynamic: author
Dynamic: author-email
Dynamic: classifier
Dynamic: description
Dynamic: description-content-type
Dynamic: home-page
Dynamic: license
Dynamic: requires-python
Dynamic: summary
